mlx_embedding_models/__init__.py
mlx_embedding_models/clip_model.py
mlx_embedding_models/embedding.py
mlx_embedding_models/load_utils.py
mlx_embedding_models/model.py
mlx_embedding_models/nomic_model.py
mlx_embedding_models/registry.py
mlx_embedding_models/test_mteb.py
mlx_embedding_models-0.0.11.dist-info/LICENSE
mlx_embedding_models-0.0.11.dist-info/METADATA
mlx_embedding_models-0.0.11.dist-info/WHEEL
mlx_embedding_models-0.0.11.dist-info/top_level.txt
mlx_embedding_models-0.0.11.dist-info/RECORD
