Metadata-Version: 2.1
Name: mlx_embedding_models
Version: 0.0.11
Summary: Python utility for text embeddings in MLX.
Author-email: Benjamin Anderson <ben@trytaylor.ai>
Requires-Python: >=3.9
License-File: LICENSE
Requires-Dist: torch
Requires-Dist: transformers
Requires-Dist: mlx>=0.17.0
Requires-Dist: awkward
Requires-Dist: numpy
Requires-Dist: scipy
Requires-Dist: tqdm
